imgshift/__init__.py
imgshift/cli.py
imgshift/core.py
imgshift/utils.py
imgshift/formats/__init__.py
imgshift/formats/jpeg.py
imgshift/formats/pdf.py
imgshift/formats/png.py
imgshift/svg/__init__.py
imgshift/svg/elements.py
imgshift/svg/geometry.py
imgshift/svg/paint.py
imgshift/svg/parser.py
imgshift/svg/path_parser.py
imgshift/svg/rasterizer.py
imgshift/svg/render.py
imgshift/svg/render_context.py
imgshift/svg/transforms.py
imgshift/svg/engines/__init__.py
imgshift/svg/engines/base.py
imgshift/svg/engines/exceptions.py
imgshift/svg/engines/python_engine.py
imgshift/svg/engines/resvg_engine.py
imgshift-0.1.2.dist-info/METADATA
imgshift-0.1.2.dist-info/WHEEL
imgshift-0.1.2.dist-info/entry_points.txt
imgshift-0.1.2.dist-info/licenses/LICENSE
imgshift-0.1.2.dist-info/RECORD
