Metadata-Version: 2.4
Name: imgshift
Version: 0.1.2
Summary: Fast image conversion library with exceptional SVG support
Project-URL: Homepage, https://github.com/sanjaymalladi/imgshift
Project-URL: Repository, https://github.com/sanjaymalladi/imgshift
Project-URL: Issues, https://github.com/sanjaymalladi/imgshift/issues
Author-email: Sanjay <malladisanjay29@gmail.com>
License-Expression: MIT
License-File: LICENSE
Keywords: cli,converter,image,jpeg,pdf,png,rasterize,svg
Classifier: Development Status :: 4 - Beta
Classifier: Intended Audience :: Developers
Classifier: License :: OSI Approved :: MIT License
Classifier: Operating System :: OS Independent
Classifier: Programming Language :: Python :: 3
Classifier: Programming Language :: Python :: 3.9
Classifier: Programming Language :: Python :: 3.10
Classifier: Programming Language :: Python :: 3.11
Classifier: Programming Language :: Python :: 3.12
Classifier: Topic :: Multimedia :: Graphics :: Graphics Conversion
Requires-Python: >=3.9
Requires-Dist: pillow>=10.0.0
Requires-Dist: pymupdf>=1.23.0
Requires-Dist: pypng>=0.20220715.0
Requires-Dist: resvg-py>=0.2.0
Provides-Extra: dev
Requires-Dist: build; extra == 'dev'
Requires-Dist: pytest>=7.0.0; extra == 'dev'
Requires-Dist: ruff>=0.1.0; extra == 'dev'
Requires-Dist: twine; extra == 'dev'
